<annotation>
	<folder>my-project-name</folder>
	<filename>FLIR_00756.jpeg</filename>
	<path>/my-project-name/FLIR_00756.jpeg</path>
	<source>
		<database>Unspecified</database>
	</source>
	<size>
		<width>640</width>
		<height>512</height>
		<depth>3</depth>
	</size>
	<object>
		<name>car</name>
		<pose>Unspecified</pose>
		<truncated>0</truncated>
		<difficult>0</difficult>
		<bndbox>
			<xmin>186</xmin>
			<ymin>228</ymin>
			<xmax>226</xmax>
			<ymax>260</ymax>
		</bndbox>
	</object>
	<object>
		<name>car</name>
		<pose>Unspecified</pose>
		<truncated>0</truncated>
		<difficult>0</difficult>
		<bndbox>
			<xmin>226</xmin>
			<ymin>229</ymin>
			<xmax>250</xmax>
			<ymax>245</ymax>
		</bndbox>
	</object>
	<object>
		<name>car</name>
		<pose>Unspecified</pose>
		<truncated>0</truncated>
		<difficult>0</difficult>
		<bndbox>
			<xmin>258</xmin>
			<ymin>228</ymin>
			<xmax>277</xmax>
			<ymax>246</ymax>
		</bndbox>
	</object>
	<object>
		<name>car</name>
		<pose>Unspecified</pose>
		<truncated>0</truncated>
		<difficult>0</difficult>
		<bndbox>
			<xmin>282</xmin>
			<ymin>228</ymin>
			<xmax>298</xmax>
			<ymax>243</ymax>
		</bndbox>
	</object>
</annotation>